django_queryset_exts/__init__.py
django_queryset_exts/fields.py
django_queryset_exts/models.py
django_queryset_exts/query.py
django_queryset_exts/signals.py
django_queryset_exts-0.0.1.dist-info/LICENSE
django_queryset_exts-0.0.1.dist-info/METADATA
django_queryset_exts-0.0.1.dist-info/WHEEL
django_queryset_exts-0.0.1.dist-info/top_level.txt
django_queryset_exts-0.0.1.dist-info/RECORD
