Metadata-Version: 2.1
Name: django-queryset-exts
Version: 0.0.1
Summary: A django queryset with a select_related(or prefetch_related) like method to fetch remote(e.g., api) data.
Home-page: https://github.com/zzhhss/django-queryset-exts
Author: zzhhss
Author-email: clayhaw@163.com
License: UNKNOWN
Platform: UNKNOWN
Classifier: Programming Language :: Python :: 3
Classifier: License :: OSI Approved :: MIT License
Classifier: Operating System :: OS Independent
Requires-Python: >=3.6
